[
  { "name": "ALBA", "alpha2": "AB", "alpha3": "RO-AB" },
  { "name": "ARAD", "alpha2": "AR", "alpha3": "RO-AR" },
  { "name": "ARGES", "alpha2": "AG", "alpha3": "RO-AG" },
  { "name": "BACAU", "alpha2": "BC", "alpha3": "RO-BC" },
  { "name": "BIHOR", "alpha2": "BH", "alpha3": "RO-BH" },
  { "name": "BISTRITA-NASAUD", "alpha2": "BN", "alpha3": "RO-BN" },
  { "name": "BOTOSANI", "alpha2": "BT", "alpha3": "RO-BT" },
  { "name": "BRASOV", "alpha2": "BV", "alpha3": "RO-BV" },
  { "name": "BRAILA", "alpha2": "BR", "alpha3": "RO-BR" },
  { "name": "SECTOR 1 (BUCURESTI)", "alpha2": "B1", "alpha3": "SECTOR1" },
  { "name": "SECTOR 2 (BUCURESTI)", "alpha2": "B2", "alpha3": "SECTOR2" },
  { "name": "SECTOR 3 (BUCURESTI)", "alpha2": "B3", "alpha3": "SECTOR3" },
  { "name": "SECTOR 4 (BUCURESTI)", "alpha2": "B4", "alpha3": "SECTOR4" },
  { "name": "SECTOR 5 (BUCURESTI)", "alpha2": "B5", "alpha3": "SECTOR5" },
  { "name": "SECTOR 6 (BUCURESTI)", "alpha2": "B6", "alpha3": "SECTOR6" },
  { "name": "BUZAU", "alpha2": "BZ", "alpha3": "RO-BZ" },
  { "name": "CARAS-SEVERIN", "alpha2": "CS", "alpha3": "RO-CS" },
  { "name": "CALARASI", "alpha2": "CL", "alpha3": "RO-CL" },
  { "name": "CLUJ", "alpha2": "CJ", "alpha3": "RO-CJ" },
  { "name": "CONSTANTA", "alpha2": "CT", "alpha3": "RO-CT" },
  { "name": "COVASNA", "alpha2": "CV", "alpha3": "RO-CV" },
  { "name": "DAMBOVITA", "alpha2": "DB", "alpha3": "RO-DB" },
  { "name": "DOLJ", "alpha2": "DJ", "alpha3": "RO-DJ" },
  { "name": "GALATI", "alpha2": "GL", "alpha3": "RO-GL" },
  { "name": "GIURGIU", "alpha2": "GR", "alpha3": "RO-GR" },
  { "name": "GORJ", "alpha2": "GJ", "alpha3": "RO-GJ" },
  { "name": "HARGHITA", "alpha2": "HR", "alpha3": "RO-HR" },
  { "name": "HUNEDOARA", "alpha2": "HD", "alpha3": "RO-HD" },
  { "name": "IALOMITA", "alpha2": "IL", "alpha3": "RO-IL" },
  { "name": "IASI", "alpha2": "IS", "alpha3": "RO-IS" },
  { "name": "ILFOV", "alpha2": "IF", "alpha3": "RO-IF" },
  { "name": "MARAMURES", "alpha2": "MM", "alpha3": "RO-MM" },
  { "name": "MEHEDINTI", "alpha2": "MH", "alpha3": "RO-MH" },
  { "name": "MURES", "alpha2": "MS", "alpha3": "RO-MS" },
  { "name": "NEAMT", "alpha2": "NT", "alpha3": "RO-NT" },
  { "name": "OLT", "alpha2": "OT", "alpha3": "RO-OT" },
  { "name": "PRAHOVA", "alpha2": "PH", "alpha3": "RO-PH" },
  { "name": "SATU-MARE", "alpha2": "SM", "alpha3": "RO-SM" },
  { "name": "SALAJ", "alpha2": "SJ", "alpha3": "RO-SJ" },
  { "name": "SIBIU", "alpha2": "SB", "alpha3": "RO-SB" },
  { "name": "SUCEAVA", "alpha2": "SV", "alpha3": "RO-SV" },
  { "name": "TELEORMAN", "alpha2": "TR", "alpha3": "RO-TR" },
  { "name": "TIMIS", "alpha2": "TM", "alpha3": "RO-TM" },
  { "name": "TULCEA", "alpha2": "TL", "alpha3": "RO-TL" },
  { "name": "VASLUI", "alpha2": "VS", "alpha3": "RO-VS" },
  { "name": "VALCEA", "alpha2": "VL", "alpha3": "RO-VL" },
  { "name": "VRANCEA", "alpha2": "VN", "alpha3": "RO-VN" }
]
